simple_lombok/__init__.py
simple_lombok/constructor.py
simple_lombok/data_class.py
simple_lombok/decorators.py
simple_lombok/immutable.py
simple_lombok/logger.py
simple_lombok/validation.py
simple_lombok-1.0.0.dist-info/licenses/LICENSE
simple_lombok-1.0.0.dist-info/METADATA
simple_lombok-1.0.0.dist-info/WHEEL
simple_lombok-1.0.0.dist-info/top_level.txt
simple_lombok-1.0.0.dist-info/RECORD
