Metadata-Version: 2.4
Name: simple-lombok
Version: 1.0.0
Summary: A Python library inspired by Java's Lombok for reducing boilerplate code.
Home-page: https://github.com/nikita20002000/simple_lombok
Author: Nikita20002000
Author-email: novikov.nikita.work@yandex.ru
Classifier: Programming Language :: Python :: 3
Classifier: License :: OSI Approved :: MIT License
Classifier: Operating System :: OS Independent
Requires-Python: >=3.6
License-File: LICENSE
Dynamic: author
Dynamic: author-email
Dynamic: classifier
Dynamic: description
Dynamic: description-content-type
Dynamic: home-page
Dynamic: license-file
Dynamic: requires-python
Dynamic: summary
